core/__init__.py
core/aws_requester.py
core/exceptions.py
core/logging.py
core/py.typed
core/requester.py
core/s3_manager.py
core/service_client.py
core/api/__init__.py
core/api/health.py
core/api/middleware/__init__.py
core/api/middleware/database_connection_middleware.py
core/api/middleware/exception_handling_middleware.py
core/api/middleware/logging_middleware.py
core/api/middleware/server_headers_middleware.py
core/http/__init__.py
core/http/basic_authentication.py
core/notifications/__init__.py
core/notifications/discord_client.py
core/notifications/notification_client.py
core/notifications/slack_client.py
core/queues/__init__.py
core/queues/aqs.py
core/queues/message_queue.py
core/queues/message_queue_processor.py
core/queues/model.py
core/queues/sqs.py
core/store/__init__.py
core/store/database.py
core/store/retriever.py
core/store/saver.py
core/util/__init__.py
core/util/chain_util.py
core/util/date_util.py
core/util/dict_util.py
core/util/file_util.py
core/util/hashing_util.py
core/util/list_util.py
core/util/string_util.py
core/util/typing_util.py
core/util/value_holder.py
core/web3/__init__.py
core/web3/eth_client.py
kiba_core-0.5.2.dist-info/METADATA
kiba_core-0.5.2.dist-info/WHEEL
kiba_core-0.5.2.dist-info/top_level.txt
kiba_core-0.5.2.dist-info/RECORD
